gptsession/__init__.py
gptsession/conversation.py
gptsession-1.0.0.dist-info/licenses/LICENSE
gptsession-1.0.0.dist-info/METADATA
gptsession-1.0.0.dist-info/WHEEL
gptsession-1.0.0.dist-info/top_level.txt
gptsession-1.0.0.dist-info/RECORD
