Metadata-Version: 2.4
Name: gptsession
Version: 1.0.0
Summary: simple, stateful conversations with OpenAI's chat models, including truncation and token metering
Author-email: Lion Kimbro <lionkimbro@gmail.com>
License-Expression: MIT
Project-URL: Homepage, https://github.com/LionKimbro/gptsession
Project-URL: Bug Tracker, https://github.com/LionKimbro/gptsession/issues
Classifier: Programming Language :: Python :: 3
Classifier: Programming Language :: Python :: 3.7
Classifier: Programming Language :: Python :: 3.8
Classifier: Programming Language :: Python :: 3.9
Classifier: Programming Language :: Python :: 3.10
Classifier: Programming Language :: Python :: 3.11
Classifier: Operating System :: OS Independent
Requires-Python: >=3.7
License-File: LICENSE
Requires-Dist: openai
Requires-Dist: tiktoken
Dynamic: license-file
